Metadata-Version: 2.1
Name: bad-helloworld-1
Version: 1.0
Summary: hello world to break dependencies...
Home-page: UNKNOWN
License: UNKNOWN
Platform: UNKNOWN
Classifier: Programming Language :: Python :: 3.9
Classifier: License :: OSI Approved :: MIT License
Classifier: Operating System :: OS Independent
Requires-Python: >=3.9
License-File: LICENSE.txt
Requires-Dist: numpy (==1.21.1)
